object_registry/__init__.py
object_registry-0.3.0.dist-info/LICENSE
object_registry-0.3.0.dist-info/METADATA
object_registry-0.3.0.dist-info/WHEEL
object_registry-0.3.0.dist-info/RECORD
