Metadata-Version: 2.1
Name: object-registry
Version: 0.3.0
Summary: Keep track of all instantiated objects of a class.
Home-page: https://gitlab.com/deepadmax/object-registry
License: GPL-3.0-or-later
Author: Maximillian Strand
Author-email: maxi@millian.se
Requires-Python: >=3.11,<4.0
Classifier: License :: OSI Approved :: GNU General Public License v3 or later (GPLv3+)
Classifier: Programming Language :: Python :: 3
Classifier: Programming Language :: Python :: 3.11
Project-URL: Repository, https://gitlab.com/deepadmax/object-registry
